fints/__init__.py
fints/client.py
fints/connection.py
fints/dialog.py
fints/exceptions.py
fints/fields.py
fints/formals.py
fints/message.py
fints/models.py
fints/parser.py
fints/security.py
fints/types.py
fints/utils.py
fints/hhd/__init__.py
fints/hhd/flicker.py
fints/segments/__init__.py
fints/segments/accounts.py
fints/segments/auth.py
fints/segments/bank.py
fints/segments/base.py
fints/segments/debit.py
fints/segments/depot.py
fints/segments/dialog.py
fints/segments/journal.py
fints/segments/message.py
fints/segments/saldo.py
fints/segments/statement.py
fints/segments/transfer.py
fints-4.2.4.dist-info/licenses/LICENSE.txt
fints-4.2.4.dist-info/METADATA
fints-4.2.4.dist-info/WHEEL
fints-4.2.4.dist-info/top_level.txt
fints-4.2.4.dist-info/RECORD
