Metadata-Version: 2.4
Name: fints
Version: 4.2.4
Summary: Pure-python FinTS 3.0 (formerly known as HBCI) implementation
Author-email: Raphael Michel <mail@raphaelmichel.de>
License-Expression: LGPL-3.0-or-later
Project-URL: Homepage, https://github.com/raphaelm/python-fints
Keywords: hbci,banking,fints
Classifier: Development Status :: 4 - Beta
Classifier: Intended Audience :: Developers
Classifier: Intended Audience :: Other Audience
Classifier: Programming Language :: Python :: 3.9
Classifier: Programming Language :: Python :: 3.10
Classifier: Programming Language :: Python :: 3.11
Classifier: Programming Language :: Python :: 3.12
Requires-Python: >=3.9
License-File: LICENSE.txt
Requires-Dist: bleach
Requires-Dist: mt-940
Requires-Dist: requests
Requires-Dist: sepaxml~=2.1
Requires-Dist: enum-tools~=0.12.0
Dynamic: license-file
